Metadata-Version: 2.1
Name: factorio-check
Version: 0.0.11
Summary: A library for helping with factorio testing
Author-email: Danny Farrell <16297104+danpf@users.noreply.github.com>
License: MIT License
Project-URL: Homepage, https://github.com/danpf/factorio-check
Classifier: Development Status :: 4 - Beta
Classifier: Programming Language :: Python
Requires-Python: >=3.10
License-File: LICENSE
